{"Device_set": "square_4by4", "M": 8, "D": 33, "g1": 12, "g2": 27, "extra_edge_num": 5, "extra_edge": [[2, 7], [1, 6], [10, 13], [7, 10], [5, 10]], "benchmark": "qaoa", "gates": [[[5, 10]], [[7, 10], [1, 5]], [[10, 11]], [[10, 13]], [[5, 10]], [[10, 11]], [[6, 10], [7, 11]], [[1, 6]], [[2, 6]], [[1, 2]], [[2, 7]]], "gate_spec": [[" ZZ"], [" ZZ", " ZZ"], [" ZZ"], [" swap"], [" ZZ"], [" ZZ"], [" ZZ", " ZZ"], [" ZZ"], [" ZZ"], [" ZZ"], [" ZZ"]], "initial_mapping": [10, 1, 11, 6, 13, 2, 7, 5], "final_mapping": [13, 1, 11, 6, 10, 2, 7, 5], "olsq_mode": "transition", "crosstalk": 8, "fidelity": 0.6179392841594575, "fidelity_ct": 0.5934089505721943}