{"Device_set": "hh", "M": 8, "D": 18, "g1": 12, "g2": 24, "extra_edge_num": 6, "extra_edge": [[3, 12], [5, 14], [0, 3], [0, 5], [12, 17], [14, 17]], "benchmark": "qaoa", "gates": [[[4, 5], [13, 12]], [[4, 3], [5, 14]], [[4, 0], [13, 14], [12, 3]], [[5, 0], [13, 17]], [[12, 17], [3, 0]], [[14, 17]]], "gate_spec": [["ZZ", "ZZ"], ["ZZ", "ZZ"], ["ZZ", "ZZ", "ZZ"], ["ZZ", "ZZ"], ["ZZ", "ZZ"], ["ZZ"]], "initial_mapping": [4, 5, 13, 3, 12, 17, 0, 14], "final_mapping": [4, 5, 13, 3, 12, 17, 0, 14], "olsq_mode": "transition", "crosstalk": 22, "fidelity": 0.7137560337288861, "fidelity_ct": 0.6385171733132036}