{"Device_set": "hh", "M": 10, "D": 24, "g1": 15, "g2": 36, "extra_edge_num": 6, "extra_edge": [[3, 8], [8, 12], [4, 14], [5, 14], [6, 14], [9, 14]], "benchmark": "qaoa", "gates": [[[6, 14], [11, 12]], [[6, 9], [14, 4], [11, 8]], [[6, 5], [14, 13], [3, 8]], [[11, 8], [12, 13], [9, 14]], [[12, 8], [14, 13]], [[14, 5], [8, 3]], [[3, 4]], [[4, 5]]], "gate_spec": [["ZZ", "ZZ"], ["ZZ", "ZZ", "ZZ"], ["ZZ", "ZZ", "SWAP"], ["ZZ", "ZZ", "SWAP"], ["ZZ", "ZZ"], ["ZZ", "ZZ"], ["ZZ"], ["ZZ"]], "initial_mapping": [6, 14, 3, 11, 9, 5, 4, 8, 12, 13], "final_mapping": [6, 9, 8, 11, 14, 5, 4, 3, 12, 13], "olsq_mode": "transition", "crosstalk": 20, "fidelity": 0.5887111661071995, "fidelity_ct": 0.5320139145247933}